miniapp_scraping/__init__.py
miniapp_scraping/cli.py
miniapp_scraping/scraper.py
miniapp_scraping-1.4.0.dist-info/licenses/LICENSE
miniapp_scraping-1.4.0.dist-info/METADATA
miniapp_scraping-1.4.0.dist-info/WHEEL
miniapp_scraping-1.4.0.dist-info/entry_points.txt
miniapp_scraping-1.4.0.dist-info/top_level.txt
miniapp_scraping-1.4.0.dist-info/RECORD
