Metadata-Version: 2.4
Name: miniapp-scraping
Version: 1.4.0
Summary: Lightweight web scraping tool with email extraction
Home-page: https://github.com/TECHFUND/miniapp-scraping
Author: TECHFUND Development Team
Author-email: dev@techfund.jp
Project-URL: Bug Tracker, https://github.com/TECHFUND/miniapp-scraping/issues
Project-URL: Documentation, https://github.com/TECHFUND/miniapp-scraping#readme
Project-URL: Source Code, https://github.com/TECHFUND/miniapp-scraping
Project-URL: Changelog, https://github.com/TECHFUND/miniapp-scraping/blob/main/CHANGELOG.md
Keywords: scraping,miniapp,press-release,email-extraction,web-scraping,data-extraction,journalism,media,automation
Classifier: Development Status :: 5 - Production/Stable
Classifier: Intended Audience :: Developers
Classifier: Intended Audience :: Information Technology
Classifier: License :: OSI Approved :: MIT License
Classifier: Operating System :: OS Independent
Classifier: Programming Language :: Python :: 3
Classifier: Programming Language :: Python :: 3.8
Classifier: Programming Language :: Python :: 3.9
Classifier: Programming Language :: Python :: 3.10
Classifier: Programming Language :: Python :: 3.11
Classifier: Programming Language :: Python :: 3.12
Classifier: Topic :: Internet :: WWW/HTTP :: Indexing/Search
Classifier: Topic :: Software Development :: Libraries :: Python Modules
Classifier: Topic :: Text Processing :: Markup :: HTML
Classifier: Topic :: Communications :: Email
Requires-Python: >=3.8
License-File: LICENSE
Requires-Dist: requests>=2.25.1
Requires-Dist: beautifulsoup4>=4.9.3
Requires-Dist: lxml>=4.6.3
Provides-Extra: dev
Requires-Dist: black>=22.0.0; extra == "dev"
Requires-Dist: flake8>=4.0.0; extra == "dev"
Requires-Dist: pytest>=7.0.0; extra == "dev"
Dynamic: author
Dynamic: author-email
Dynamic: classifier
Dynamic: description
Dynamic: description-content-type
Dynamic: home-page
Dynamic: keywords
Dynamic: license-file
Dynamic: project-url
Dynamic: provides-extra
Dynamic: requires-dist
Dynamic: requires-python
Dynamic: summary
